[
    {
        "key":"1",
        "title":"Menu 1",
        "content":
        [
            {
                "title": "test Sub Menu Item 1 1",
                "label": "Sub Menu Item 1 1",
                "key": "3",
                "content":
                [
                    {
                        "key":"2",
                        "title":" test My Career and benefits",
                        "content":
                        [
                            {
                                "key":"2",
                                "title":"test 1",
                                "content":"My Career and benefits 1"
                            },
                            
                            {
                                "key":"2",
                                "title":"test2 ",
                                "content":"My Career and benefits 1"
                            },
                            {
                                "key":"2",
                                "title":"test3",
                                "content":"My Career and benefits 1"
                            }
                            
                        ]
                    },
                    {
                        "key":"3",
                        "title":" test My Career and benefits 2",
                        "content":
                        [
                            {
                                "key":"2",
                                "title":"test 1",
                                "content":"My Career and benefits 1"
                            },
                            
                            {
                                "key":"2",
                                "title":"test2 ",
                                "content":"My Career and benefits 1"
                            },
                            {
                                "key":"2",
                                "title":"test3",
                                "content":"My Career and benefits 1"
                            }
                            
                        ]
                    },
                    {
                        "key":"4",
                        "title":" test My Career and benefits 3",
                        "content":
                        [
                            {
                                "key":"2",
                                "title":"test 1",
                                "content":"My Career and benefits 1"
                            },
                            
                            {
                                "key":"2",
                                "title":"test2 ",
                                "content":"My Career and benefits 1"
                            },
                            {
                                "key":"2",
                                "title":"test3",
                                "content":"My Career and benefits 1"
                            }
                            
                        ]
                    }
                ]
            },
            {
                "title": "Sub Menu Item 1 2",
                "label": "Sub Menu Item 1 2",
                "key": "5",
                "content":
                [
                    {
                        "key":"6",
                        "title":"My Career and benefits",
                        "content":
                        [
                            {
                                "key":"2",
                                "title":"test 1",
                                "content":"My Career and benefits 1"
                            },
                            
                            {
                                "key":"2",
                                "title":"test2 ",
                                "content":"My Career and benefits 1"
                            },
                            {
                                "key":"2",
                                "title":"test3",
                                "content":"My Career and benefits 1"
                            }
                            
                        ]
                    },
                    {
                        "key":"7",
                        "title":"My Career and benefits 2",
                        "content":
                        [
                            {
                                "key":"2",
                                "title":"test 1",
                                "content":"My Career and benefits 1"
                            },
                            
                            {
                                "key":"2",
                                "title":"test2 ",
                                "content":"My Career and benefits 1"
                            },
                            {
                                "key":"2",
                                "title":"test3",
                                "content":"My Career and benefits 1"
                            }
                            
                        ]
                    },
                    {
                        "key":"8",
                        "title":"My Career and benefits 3",
                        "content":
                        [
                            {
                                "key":"2",
                                "title":"test 1",
                                "content":"My Career and benefits 1"
                            },
                            
                            {
                                "key":"2",
                                "title":"test2 ",
                                "content":"My Career and benefits 1"
                            },
                            {
                                "key":"2",
                                "title":"test3",
                                "content":"My Career and benefits 1"
                            }
                            
                        ]
                    }
                ]
            }
            
        ]
    },
    {
        "key":"1",
        "title":"Menu 1",
        "content":
        [
            {
                "title": "test Sub Menu Item 1 1",
                "label": "Sub Menu Item 1 1",
                "key": "3",
                "content":
                [
                    {
                        "key":"2",
                        "title":" test My Career and benefits",
                        "content":
                        [
                            {
                                "key":"2",
                                "title":"test 1",
                                "content":"My Career and benefits 1"
                            },
                            
                            {
                                "key":"2",
                                "title":"test2 ",
                                "content":"My Career and benefits 1"
                            },
                            {
                                "key":"2",
                                "title":"test3",
                                "content":"My Career and benefits 1"
                            }
                            
                        ]
                    },
                    {
                        "key":"3",
                        "title":" test My Career and benefits 2",
                        "content":
                        [
                            {
                                "key":"2",
                                "title":"test 1",
                                "content":"My Career and benefits 1"
                            },
                            
                            {
                                "key":"2",
                                "title":"test2 ",
                                "content":"My Career and benefits 1"
                            },
                            {
                                "key":"2",
                                "title":"test3",
                                "content":"My Career and benefits 1"
                            }
                            
                        ]
                    },
                    {
                        "key":"4",
                        "title":" test My Career and benefits 3",
                        "content":
                        [
                            {
                                "key":"2",
                                "title":"test 1",
                                "content":"My Career and benefits 1"
                            },
                            
                            {
                                "key":"2",
                                "title":"test2 ",
                                "content":"My Career and benefits 1"
                            },
                            {
                                "key":"2",
                                "title":"test3",
                                "content":"My Career and benefits 1"
                            }
                            
                        ]
                    }
                ]
            },
            {
                "title": "Sub Menu Item 1 2",
                "label": "Sub Menu Item 1 2",
                "key": "5",
                "content":
                [
                    {
                        "key":"6",
                        "title":"My Career and benefits",
                        "content":
                        [
                            {
                                "key":"2",
                                "title":"test 1",
                                "content":"My Career and benefits 1"
                            },
                            
                            {
                                "key":"2",
                                "title":"test2 ",
                                "content":"My Career and benefits 1"
                            },
                            {
                                "key":"2",
                                "title":"test3",
                                "content":"My Career and benefits 1"
                            }
                            
                        ]
                    },
                    {
                        "key":"7",
                        "title":"My Career and benefits 2",
                        "content":
                        [
                            {
                                "key":"2",
                                "title":"test 1",
                                "content":"My Career and benefits 1"
                            },
                            
                            {
                                "key":"2",
                                "title":"test2 ",
                                "content":"My Career and benefits 1"
                            },
                            {
                                "key":"2",
                                "title":"test3",
                                "content":"My Career and benefits 1"
                            }
                            
                        ]
                    },
                    {
                        "key":"8",
                        "title":"My Career and benefits 3",
                        "content":
                        [
                            {
                                "key":"2",
                                "title":"test 1",
                                "content":"My Career and benefits 1"
                            },
                            
                            {
                                "key":"2",
                                "title":"test2 ",
                                "content":"My Career and benefits 1"
                            },
                            {
                                "key":"2",
                                "title":"test3",
                                "content":"My Career and benefits 1"
                            }
                            
                        ]
                    }
                ]
            }
            
        ]
    }
]